DebugUI/__init__.py
DebugUI-0.2.2.dist-info/METADATA
DebugUI-0.2.2.dist-info/WHEEL
DebugUI-0.2.2.dist-info/top_level.txt
DebugUI-0.2.2.dist-info/RECORD
